wagtail_shiki/__init__.py
wagtail_shiki/_version.py
wagtail_shiki/blocks.py
wagtail_shiki/settings.py
wagtail_shiki/static/wagtail_shiki/css/decorations.css
wagtail_shiki/static/wagtail_shiki/css/wagtail-shiki-admin.css
wagtail_shiki/static/wagtail_shiki/css/wagtail-shiki.css
wagtail_shiki/static/wagtail_shiki/css/title-block/title-block-inside-bg-gray.css
wagtail_shiki/static/wagtail_shiki/css/title-block/title-block-outside-bg-gray.css
wagtail_shiki/static/wagtail_shiki/css/title-block/title-block-simple.css
wagtail_shiki/static/wagtail_shiki/css/title-block/title-block-underline.css
wagtail_shiki/static/wagtail_shiki/css/title-block/title-block.css
wagtail_shiki/static/wagtail_shiki/js/wagtail-shiki-admin.js
wagtail_shiki/static/wagtail_shiki/js/wagtail-shiki.js
wagtail_shiki/templates/wagtail_shiki/code_block.html
wagtail_shiki/templates/wagtail_shiki/code_block_form.html
wagtail_shiki/templatetags/__init__.py
wagtail_shiki/templatetags/wagtail_shiki_tags.py
wagtail_shiki-1.1.0.dist-info/licenses/LICENSE
wagtail_shiki-1.1.0.dist-info/METADATA
wagtail_shiki-1.1.0.dist-info/WHEEL
wagtail_shiki-1.1.0.dist-info/top_level.txt
wagtail_shiki-1.1.0.dist-info/RECORD
