Metadata-Version: 2.4
Name: wagtail-shiki
Version: 1.1.0
Summary: Add a code block to StreamField of Wagtail with Shiki Syntax highlighter.
Author-email: kawakin <kawakin26@gmail.com>
License: BSD-3-Clause
Project-URL: Homepage, https://github.com/kawakin26/wagtail-shiki
Project-URL: Repository, https://github.com/kawakin26/wagtail-shiki
Project-URL: Documentation, https://github.com/kawakin26/wagtail-shiki
Keywords: wagtail,shiki,cms,syntax,code,highlighting,highlighter
Classifier: Development Status :: 5 - Production/Stable
Classifier: Environment :: Web Environment
Classifier: Intended Audience :: Developers
Classifier: License :: OSI Approved :: BSD License
Classifier: Operating System :: OS Independent
Classifier: Programming Language :: Python :: 3.9
Classifier: Programming Language :: Python :: 3.10
Classifier: Programming Language :: Python :: 3.11
Classifier: Programming Language :: Python :: 3.12
Classifier: Programming Language :: Python :: 3.13
Classifier: Framework :: Django :: 4.2
Classifier: Framework :: Django :: 5.1
Classifier: Framework :: Django :: 5.2
Classifier: Framework :: Wagtail :: 4
Classifier: Framework :: Wagtail :: 5
Classifier: Framework :: Wagtail :: 6
Classifier: Framework :: Wagtail :: 7
Requires-Python: >=3.9
License-File: LICENSE
Requires-Dist: wagtail>=4
Provides-Extra: dev
Requires-Dist: django-coverage-plugin; extra == "dev"
Requires-Dist: ipython; extra == "dev"
Requires-Dist: ruff; extra == "dev"
Requires-Dist: pytest-coverage; extra == "dev"
Requires-Dist: pytest-django; extra == "dev"
Dynamic: license-file
